character_encoding_utils/__init__.py
character_encoding_utils/big5.py
character_encoding_utils/gb2312.py
character_encoding_utils/ksx1001.py
character_encoding_utils/shiftjis.py
character_encoding_utils-0.0.12.dist-info/WHEEL
character_encoding_utils-0.0.12.dist-info/METADATA
character_encoding_utils-0.0.12.dist-info/RECORD
