Metadata-Version: 2.4
Name: character-encoding-utils
Version: 0.0.12
Summary: Some character encoding utils
Keywords: encoding,gb2312,big5,shift-jis,ksx1001
Author: TakWolf
License-Expression: MIT
Classifier: Programming Language :: Python :: 3
Classifier: Programming Language :: Python :: 3.10
Classifier: Programming Language :: Python :: 3.11
Classifier: Programming Language :: Python :: 3.12
Classifier: Programming Language :: Python :: 3.13
Classifier: Programming Language :: Python :: 3.14
Classifier: License :: OSI Approved :: MIT License
Classifier: Operating System :: OS Independent
Maintainer: TakWolf
Requires-Python: >=3.10
Project-URL: Homepage, https://github.com/TakWolf/character-encoding-utils
Project-URL: Issues, https://github.com/TakWolf/character-encoding-utils/issues
Project-URL: Source, https://github.com/TakWolf/character-encoding-utils
